stackable/VERSION
stackable/__init__.py
stackable/crypto.py
stackable/encryptkeys.py
stackable/stackable.py
stackable/contrib/__init__.py
stackable/contrib/config/__init__.py
stackable/contrib/config/conf_DjangoFormats.py
stackable/contrib/config/conf_admin.py
stackable/contrib/config/conf_allauth.py
stackable/contrib/config/conf_api.py
stackable/contrib/config/conf_aws.py
stackable/contrib/config/conf_axes.py
stackable/contrib/config/conf_bootstrap.py
stackable/contrib/config/conf_cache.py
stackable/contrib/config/conf_celery.py
stackable/contrib/config/conf_cities_light.py
stackable/contrib/config/conf_cms.py
stackable/contrib/config/conf_cmscascade.py
stackable/contrib/config/conf_collectfast.py
stackable/contrib/config/conf_constance.py
stackable/contrib/config/conf_corsmiddleware.py
stackable/contrib/config/conf_dbdump.py
stackable/contrib/config/conf_debugperm.py
stackable/contrib/config/conf_debugtoolbar.py
stackable/contrib/config/conf_djangoadmin.py
stackable/contrib/config/conf_djangocmsext.py
stackable/contrib/config/conf_djangoextensions.py
stackable/contrib/config/conf_djangograppelli.py
stackable/contrib/config/conf_djangologging.py
stackable/contrib/config/conf_djangonose.py
stackable/contrib/config/conf_djcelery.py
stackable/contrib/config/conf_dokku.py
stackable/contrib/config/conf_fullhttps.py
stackable/contrib/config/conf_getstream.py
stackable/contrib/config/conf_guardian.py
stackable/contrib/config/conf_model_l10n.py
stackable/contrib/config/conf_nomigrations.py
stackable/contrib/config/conf_payment.py
stackable/contrib/config/conf_postman.py
stackable/contrib/config/conf_postoffice.py
stackable/contrib/config/conf_sekizai.py
stackable/contrib/config/conf_static.py
stackable/contrib/config/conf_swagger.py
stackable/contrib/config/conf_teamcity.py
stackable/contrib/config/conf_whitenoise.py
stackable/contrib/config/conf_zinnia.py
stackable/contrib/config/email/__init__.py
stackable/contrib/config/email/async.py
stackable-0.6.0.dist-info/LICENSE
stackable-0.6.0.dist-info/METADATA
stackable-0.6.0.dist-info/WHEEL
stackable-0.6.0.dist-info/pbr.json
stackable-0.6.0.dist-info/top_level.txt
stackable-0.6.0.dist-info/RECORD
