Metadata-Version: 2.1
Name: stackable
Version: 0.6.0
Summary: stackable settings for any Python and Django application
Home-page: https://github.com/productaize/stackable
Author: miraculixx
Author-email: miraculixx@gmx.ch
License: MIT
Platform: UNKNOWN
Classifier: Environment :: Web Environment
Classifier: Framework :: Django
Classifier: Intended Audience :: Developers
Classifier: License :: OSI Approved :: MIT License
Classifier: Operating System :: OS Independent
Classifier: Programming Language :: Python
Classifier: Programming Language :: Python :: 2
Classifier: Programming Language :: Python :: 2.7
Classifier: Topic :: Internet :: WWW/HTTP
Classifier: Topic :: Internet :: WWW/HTTP :: Dynamic Content
License-File: LICENSE
Requires-Dist: pyyaml (>3.11)
Requires-Dist: ordered-set
Requires-Dist: pyaes
